MANIFEST.in
README.rst
alchmanager.py
setup.py
tests.py
sqlalchemy_manager.egg-info/PKG-INFO
sqlalchemy_manager.egg-info/SOURCES.txt
sqlalchemy_manager.egg-info/dependency_links.txt
sqlalchemy_manager.egg-info/not-zip-safe
sqlalchemy_manager.egg-info/requires.txt
sqlalchemy_manager.egg-info/top_level.txt