Metadata-Version: 1.1
Name: sqlalchemy-manager
Version: 0.0.2
Summary: Manager for SQLAlchemy
Home-page: https://github.com/d1ffuz0r/sqlalchemy-manager
Author: Roman Gladkov
Author-email: d1fffuz0r@gmail.com
License: UNKNOWN
Platform: UNKNOWN
Classifier: Intended Audience :: Developers
Classifier: Programming Language :: Python
Classifier: Programming Language :: Python :: 2.7
Classifier: Programming Language :: Python :: 3.3
